examples/01_helium.py
examples/02_h2_dissociation.py
pyscf_vorticity/__init__.py
pyscf_vorticity/gamma.py
pyscf_vorticity/vorticity_jax.py
pyscf_vorticity/vorticity_numpy.py
pyscf_vorticity-0.1.0.dist-info/licenses/LICENSE
tests/test_vorticity.py
pyscf_vorticity-0.1.0.dist-info/METADATA
pyscf_vorticity-0.1.0.dist-info/WHEEL
pyscf_vorticity-0.1.0.dist-info/top_level.txt
pyscf_vorticity-0.1.0.dist-info/RECORD
