Metadata-Version: 2.4
Name: pyscf-vorticity
Version: 0.1.0
Summary: Λ³-DFT: Vorticity-based exchange-correlation analysis
Home-page: https://github.com/miosync-masa/pyscf-vorticity
Author: Masamichi Iizumi
Author-email: Masamichi Iizumi <m.iizumi@miosync.email>
License: MIT
Project-URL: Homepage, https://github.com/miosync-masa/pyscf-vorticity
Project-URL: Repository, https://github.com/miosync-masa/pyscf-vorticity
Requires-Python: >=3.8
License-File: LICENSE
Requires-Dist: numpy>=1.20
Requires-Dist: scipy>=1.7
Provides-Extra: pyscf
Requires-Dist: pyscf>=2.0; extra == "pyscf"
Provides-Extra: jax
Requires-Dist: jax>=0.4; extra == "jax"
Requires-Dist: jaxlib>=0.4; extra == "jax"
Provides-Extra: full
Requires-Dist: pyscf>=2.0; extra == "full"
Requires-Dist: jax>=0.4; extra == "full"
Requires-Dist: jaxlib>=0.4; extra == "full"
Dynamic: author
Dynamic: home-page
Dynamic: license-file
Dynamic: requires-python
